[{"name":"flutter_beacon_plugin","qualifiedName":"flutter_beacon_plugin","href":"flutter_beacon_plugin/flutter_beacon_plugin-library.html","type":"library","overriddenDepth":0},{"name":"Beacon","qualifiedName":"flutter_beacon_plugin.Beacon","href":"flutter_beacon_plugin/Beacon-class.html","type":"class","overriddenDepth":0,"enclosedBy":{"name":"flutter_beacon_plugin","type":"library"}},{"name":"operator ==","qualifiedName":"flutter_beacon_plugin.Beacon.==","href":"flutter_beacon_plugin/Beacon/operator_equals.html","type":"method","overriddenDepth":1,"enclosedBy":{"name":"Beacon","type":"class"}},{"name":"Beacon","qualifiedName":"flutter_beacon_plugin.Beacon.Beacon","href":"flutter_beacon_plugin/Beacon/Beacon.html","type":"constructor","overriddenDepth":0,"enclosedBy":{"name":"Beacon","type":"class"}},{"name":"accuracy","qualifiedName":"flutter_beacon_plugin.Beacon.accuracy","href":"flutter_beacon_plugin/Beacon/accuracy.html","type":"property","overriddenDepth":0,"enclosedBy":{"name":"Beacon","type":"class"}},{"name":"Beacon.fromMap","qualifiedName":"flutter_beacon_plugin.Beacon.fromMap","href":"flutter_beacon_plugin/Beacon/Beacon.fromMap.html","type":"constructor","overriddenDepth":0,"enclosedBy":{"name":"Beacon","type":"class"}},{"name":"hashCode","qualifiedName":"flutter_beacon_plugin.Beacon.hashCode","href":"flutter_beacon_plugin/Beacon/hashCode.html","type":"property","overriddenDepth":0,"enclosedBy":{"name":"Beacon","type":"class"}},{"name":"macAddress","qualifiedName":"flutter_beacon_plugin.Beacon.macAddress","href":"flutter_beacon_plugin/Beacon/macAddress.html","type":"property","overriddenDepth":0,"enclosedBy":{"name":"Beacon","type":"class"}},{"name":"major","qualifiedName":"flutter_beacon_plugin.Beacon.major","href":"flutter_beacon_plugin/Beacon/major.html","type":"property","overriddenDepth":0,"enclosedBy":{"name":"Beacon","type":"class"}},{"name":"minor","qualifiedName":"flutter_beacon_plugin.Beacon.minor","href":"flutter_beacon_plugin/Beacon/minor.html","type":"property","overriddenDepth":0,"enclosedBy":{"name":"Beacon","type":"class"}},{"name":"noSuchMethod","qualifiedName":"flutter_beacon_plugin.Beacon.noSuchMethod","href":"flutter_beacon_plugin/Beacon/noSuchMethod.html","type":"method","overriddenDepth":0,"enclosedBy":{"name":"Beacon","type":"class"}},{"name":"proximityUUID","qualifiedName":"flutter_beacon_plugin.Beacon.proximityUUID","href":"flutter_beacon_plugin/Beacon/proximityUUID.html","type":"property","overriddenDepth":0,"enclosedBy":{"name":"Beacon","type":"class"}},{"name":"rssi","qualifiedName":"flutter_beacon_plugin.Beacon.rssi","href":"flutter_beacon_plugin/Beacon/rssi.html","type":"property","overriddenDepth":0,"enclosedBy":{"name":"Beacon","type":"class"}},{"name":"runtimeType","qualifiedName":"flutter_beacon_plugin.Beacon.runtimeType","href":"flutter_beacon_plugin/Beacon/runtimeType.html","type":"property","overriddenDepth":0,"enclosedBy":{"name":"Beacon","type":"class"}},{"name":"toMap","qualifiedName":"flutter_beacon_plugin.Beacon.toMap","href":"flutter_beacon_plugin/Beacon/toMap.html","type":"method","overriddenDepth":0,"enclosedBy":{"name":"Beacon","type":"class"}},{"name":"toString","qualifiedName":"flutter_beacon_plugin.Beacon.toString","href":"flutter_beacon_plugin/Beacon/toString.html","type":"method","overriddenDepth":1,"enclosedBy":{"name":"Beacon","type":"class"}},{"name":"txPower","qualifiedName":"flutter_beacon_plugin.Beacon.txPower","href":"flutter_beacon_plugin/Beacon/txPower.html","type":"property","overriddenDepth":0,"enclosedBy":{"name":"Beacon","type":"class"}},{"name":"BluetoothState","qualifiedName":"flutter_beacon_plugin.BluetoothState","href":"flutter_beacon_plugin/BluetoothState-class.html","type":"enum","overriddenDepth":0,"enclosedBy":{"name":"flutter_beacon_plugin","type":"library"}},{"name":"operator ==","qualifiedName":"flutter_beacon_plugin.BluetoothState.==","href":"flutter_beacon_plugin/BluetoothState/operator_equals.html","type":"method","overriddenDepth":0,"enclosedBy":{"name":"BluetoothState","type":"enum"}},{"name":"hashCode","qualifiedName":"flutter_beacon_plugin.BluetoothState.hashCode","href":"flutter_beacon_plugin/BluetoothState/hashCode.html","type":"property","overriddenDepth":0,"enclosedBy":{"name":"BluetoothState","type":"enum"}},{"name":"noSuchMethod","qualifiedName":"flutter_beacon_plugin.BluetoothState.noSuchMethod","href":"flutter_beacon_plugin/BluetoothState/noSuchMethod.html","type":"method","overriddenDepth":0,"enclosedBy":{"name":"BluetoothState","type":"enum"}},{"name":"runtimeType","qualifiedName":"flutter_beacon_plugin.BluetoothState.runtimeType","href":"flutter_beacon_plugin/BluetoothState/runtimeType.html","type":"property","overriddenDepth":0,"enclosedBy":{"name":"BluetoothState","type":"enum"}},{"name":"toString","qualifiedName":"flutter_beacon_plugin.BluetoothState.toString","href":"flutter_beacon_plugin/BluetoothState/toString.html","type":"method","overriddenDepth":1,"enclosedBy":{"name":"BluetoothState","type":"enum"}},{"name":"FlutterBeaconPlugin","qualifiedName":"flutter_beacon_plugin.FlutterBeaconPlugin","href":"flutter_beacon_plugin/FlutterBeaconPlugin-class.html","type":"class","overriddenDepth":0,"enclosedBy":{"name":"flutter_beacon_plugin","type":"library"}},{"name":"operator ==","qualifiedName":"flutter_beacon_plugin.FlutterBeaconPlugin.==","href":"flutter_beacon_plugin/FlutterBeaconPlugin/operator_equals.html","type":"method","overriddenDepth":0,"enclosedBy":{"name":"FlutterBeaconPlugin","type":"class"}},{"name":"bluetoothStateStream","qualifiedName":"flutter_beacon_plugin.FlutterBeaconPlugin.bluetoothStateStream","href":"flutter_beacon_plugin/FlutterBeaconPlugin/bluetoothStateStream.html","type":"property","overriddenDepth":0,"enclosedBy":{"name":"FlutterBeaconPlugin","type":"class"}},{"name":"hashCode","qualifiedName":"flutter_beacon_plugin.FlutterBeaconPlugin.hashCode","href":"flutter_beacon_plugin/FlutterBeaconPlugin/hashCode.html","type":"property","overriddenDepth":0,"enclosedBy":{"name":"FlutterBeaconPlugin","type":"class"}},{"name":"instance","qualifiedName":"flutter_beacon_plugin.FlutterBeaconPlugin.instance","href":"flutter_beacon_plugin/FlutterBeaconPlugin/instance.html","type":"property","overriddenDepth":0,"enclosedBy":{"name":"FlutterBeaconPlugin","type":"class"}},{"name":"monitoringStream","qualifiedName":"flutter_beacon_plugin.FlutterBeaconPlugin.monitoringStream","href":"flutter_beacon_plugin/FlutterBeaconPlugin/monitoringStream.html","type":"property","overriddenDepth":0,"enclosedBy":{"name":"FlutterBeaconPlugin","type":"class"}},{"name":"noSuchMethod","qualifiedName":"flutter_beacon_plugin.FlutterBeaconPlugin.noSuchMethod","href":"flutter_beacon_plugin/FlutterBeaconPlugin/noSuchMethod.html","type":"method","overriddenDepth":0,"enclosedBy":{"name":"FlutterBeaconPlugin","type":"class"}},{"name":"permissions","qualifiedName":"flutter_beacon_plugin.FlutterBeaconPlugin.permissions","href":"flutter_beacon_plugin/FlutterBeaconPlugin/permissions.html","type":"property","overriddenDepth":0,"enclosedBy":{"name":"FlutterBeaconPlugin","type":"class"}},{"name":"rangingStream","qualifiedName":"flutter_beacon_plugin.FlutterBeaconPlugin.rangingStream","href":"flutter_beacon_plugin/FlutterBeaconPlugin/rangingStream.html","type":"property","overriddenDepth":0,"enclosedBy":{"name":"FlutterBeaconPlugin","type":"class"}},{"name":"runtimeType","qualifiedName":"flutter_beacon_plugin.FlutterBeaconPlugin.runtimeType","href":"flutter_beacon_plugin/FlutterBeaconPlugin/runtimeType.html","type":"property","overriddenDepth":0,"enclosedBy":{"name":"FlutterBeaconPlugin","type":"class"}},{"name":"startMonitoring","qualifiedName":"flutter_beacon_plugin.FlutterBeaconPlugin.startMonitoring","href":"flutter_beacon_plugin/FlutterBeaconPlugin/startMonitoring.html","type":"method","overriddenDepth":0,"enclosedBy":{"name":"FlutterBeaconPlugin","type":"class"}},{"name":"startRanging","qualifiedName":"flutter_beacon_plugin.FlutterBeaconPlugin.startRanging","href":"flutter_beacon_plugin/FlutterBeaconPlugin/startRanging.html","type":"method","overriddenDepth":0,"enclosedBy":{"name":"FlutterBeaconPlugin","type":"class"}},{"name":"toString","qualifiedName":"flutter_beacon_plugin.FlutterBeaconPlugin.toString","href":"flutter_beacon_plugin/FlutterBeaconPlugin/toString.html","type":"method","overriddenDepth":0,"enclosedBy":{"name":"FlutterBeaconPlugin","type":"class"}},{"name":"MonitoringEvent","qualifiedName":"flutter_beacon_plugin.MonitoringEvent","href":"flutter_beacon_plugin/MonitoringEvent-class.html","type":"enum","overriddenDepth":0,"enclosedBy":{"name":"flutter_beacon_plugin","type":"library"}},{"name":"operator ==","qualifiedName":"flutter_beacon_plugin.MonitoringEvent.==","href":"flutter_beacon_plugin/MonitoringEvent/operator_equals.html","type":"method","overriddenDepth":0,"enclosedBy":{"name":"MonitoringEvent","type":"enum"}},{"name":"hashCode","qualifiedName":"flutter_beacon_plugin.MonitoringEvent.hashCode","href":"flutter_beacon_plugin/MonitoringEvent/hashCode.html","type":"property","overriddenDepth":0,"enclosedBy":{"name":"MonitoringEvent","type":"enum"}},{"name":"noSuchMethod","qualifiedName":"flutter_beacon_plugin.MonitoringEvent.noSuchMethod","href":"flutter_beacon_plugin/MonitoringEvent/noSuchMethod.html","type":"method","overriddenDepth":0,"enclosedBy":{"name":"MonitoringEvent","type":"enum"}},{"name":"runtimeType","qualifiedName":"flutter_beacon_plugin.MonitoringEvent.runtimeType","href":"flutter_beacon_plugin/MonitoringEvent/runtimeType.html","type":"property","overriddenDepth":0,"enclosedBy":{"name":"MonitoringEvent","type":"enum"}},{"name":"toString","qualifiedName":"flutter_beacon_plugin.MonitoringEvent.toString","href":"flutter_beacon_plugin/MonitoringEvent/toString.html","type":"method","overriddenDepth":1,"enclosedBy":{"name":"MonitoringEvent","type":"enum"}},{"name":"MonitoringResult","qualifiedName":"flutter_beacon_plugin.MonitoringResult","href":"flutter_beacon_plugin/MonitoringResult-class.html","type":"class","overriddenDepth":0,"enclosedBy":{"name":"flutter_beacon_plugin","type":"library"}},{"name":"operator ==","qualifiedName":"flutter_beacon_plugin.MonitoringResult.==","href":"flutter_beacon_plugin/MonitoringResult/operator_equals.html","type":"method","overriddenDepth":1,"enclosedBy":{"name":"MonitoringResult","type":"class"}},{"name":"MonitoringResult","qualifiedName":"flutter_beacon_plugin.MonitoringResult.MonitoringResult","href":"flutter_beacon_plugin/MonitoringResult/MonitoringResult.html","type":"constructor","overriddenDepth":0,"enclosedBy":{"name":"MonitoringResult","type":"class"}},{"name":"event","qualifiedName":"flutter_beacon_plugin.MonitoringResult.event","href":"flutter_beacon_plugin/MonitoringResult/event.html","type":"property","overriddenDepth":0,"enclosedBy":{"name":"MonitoringResult","type":"class"}},{"name":"MonitoringResult.fromMap","qualifiedName":"flutter_beacon_plugin.MonitoringResult.fromMap","href":"flutter_beacon_plugin/MonitoringResult/MonitoringResult.fromMap.html","type":"constructor","overriddenDepth":0,"enclosedBy":{"name":"MonitoringResult","type":"class"}},{"name":"hashCode","qualifiedName":"flutter_beacon_plugin.MonitoringResult.hashCode","href":"flutter_beacon_plugin/MonitoringResult/hashCode.html","type":"property","overriddenDepth":0,"enclosedBy":{"name":"MonitoringResult","type":"class"}},{"name":"noSuchMethod","qualifiedName":"flutter_beacon_plugin.MonitoringResult.noSuchMethod","href":"flutter_beacon_plugin/MonitoringResult/noSuchMethod.html","type":"method","overriddenDepth":0,"enclosedBy":{"name":"MonitoringResult","type":"class"}},{"name":"region","qualifiedName":"flutter_beacon_plugin.MonitoringResult.region","href":"flutter_beacon_plugin/MonitoringResult/region.html","type":"property","overriddenDepth":0,"enclosedBy":{"name":"MonitoringResult","type":"class"}},{"name":"runtimeType","qualifiedName":"flutter_beacon_plugin.MonitoringResult.runtimeType","href":"flutter_beacon_plugin/MonitoringResult/runtimeType.html","type":"property","overriddenDepth":0,"enclosedBy":{"name":"MonitoringResult","type":"class"}},{"name":"state","qualifiedName":"flutter_beacon_plugin.MonitoringResult.state","href":"flutter_beacon_plugin/MonitoringResult/state.html","type":"property","overriddenDepth":0,"enclosedBy":{"name":"MonitoringResult","type":"class"}},{"name":"toMap","qualifiedName":"flutter_beacon_plugin.MonitoringResult.toMap","href":"flutter_beacon_plugin/MonitoringResult/toMap.html","type":"method","overriddenDepth":0,"enclosedBy":{"name":"MonitoringResult","type":"class"}},{"name":"toString","qualifiedName":"flutter_beacon_plugin.MonitoringResult.toString","href":"flutter_beacon_plugin/MonitoringResult/toString.html","type":"method","overriddenDepth":1,"enclosedBy":{"name":"MonitoringResult","type":"class"}},{"name":"MonitoringState","qualifiedName":"flutter_beacon_plugin.MonitoringState","href":"flutter_beacon_plugin/MonitoringState-class.html","type":"enum","overriddenDepth":0,"enclosedBy":{"name":"flutter_beacon_plugin","type":"library"}},{"name":"operator ==","qualifiedName":"flutter_beacon_plugin.MonitoringState.==","href":"flutter_beacon_plugin/MonitoringState/operator_equals.html","type":"method","overriddenDepth":0,"enclosedBy":{"name":"MonitoringState","type":"enum"}},{"name":"hashCode","qualifiedName":"flutter_beacon_plugin.MonitoringState.hashCode","href":"flutter_beacon_plugin/MonitoringState/hashCode.html","type":"property","overriddenDepth":0,"enclosedBy":{"name":"MonitoringState","type":"enum"}},{"name":"noSuchMethod","qualifiedName":"flutter_beacon_plugin.MonitoringState.noSuchMethod","href":"flutter_beacon_plugin/MonitoringState/noSuchMethod.html","type":"method","overriddenDepth":0,"enclosedBy":{"name":"MonitoringState","type":"enum"}},{"name":"runtimeType","qualifiedName":"flutter_beacon_plugin.MonitoringState.runtimeType","href":"flutter_beacon_plugin/MonitoringState/runtimeType.html","type":"property","overriddenDepth":0,"enclosedBy":{"name":"MonitoringState","type":"enum"}},{"name":"toString","qualifiedName":"flutter_beacon_plugin.MonitoringState.toString","href":"flutter_beacon_plugin/MonitoringState/toString.html","type":"method","overriddenDepth":1,"enclosedBy":{"name":"MonitoringState","type":"enum"}},{"name":"RangingResult","qualifiedName":"flutter_beacon_plugin.RangingResult","href":"flutter_beacon_plugin/RangingResult-class.html","type":"class","overriddenDepth":0,"enclosedBy":{"name":"flutter_beacon_plugin","type":"library"}},{"name":"operator ==","qualifiedName":"flutter_beacon_plugin.RangingResult.==","href":"flutter_beacon_plugin/RangingResult/operator_equals.html","type":"method","overriddenDepth":0,"enclosedBy":{"name":"RangingResult","type":"class"}},{"name":"RangingResult","qualifiedName":"flutter_beacon_plugin.RangingResult.RangingResult","href":"flutter_beacon_plugin/RangingResult/RangingResult.html","type":"constructor","overriddenDepth":0,"enclosedBy":{"name":"RangingResult","type":"class"}},{"name":"beacons","qualifiedName":"flutter_beacon_plugin.RangingResult.beacons","href":"flutter_beacon_plugin/RangingResult/beacons.html","type":"property","overriddenDepth":0,"enclosedBy":{"name":"RangingResult","type":"class"}},{"name":"RangingResult.fromMap","qualifiedName":"flutter_beacon_plugin.RangingResult.fromMap","href":"flutter_beacon_plugin/RangingResult/RangingResult.fromMap.html","type":"constructor","overriddenDepth":0,"enclosedBy":{"name":"RangingResult","type":"class"}},{"name":"hashCode","qualifiedName":"flutter_beacon_plugin.RangingResult.hashCode","href":"flutter_beacon_plugin/RangingResult/hashCode.html","type":"property","overriddenDepth":0,"enclosedBy":{"name":"RangingResult","type":"class"}},{"name":"noSuchMethod","qualifiedName":"flutter_beacon_plugin.RangingResult.noSuchMethod","href":"flutter_beacon_plugin/RangingResult/noSuchMethod.html","type":"method","overriddenDepth":0,"enclosedBy":{"name":"RangingResult","type":"class"}},{"name":"region","qualifiedName":"flutter_beacon_plugin.RangingResult.region","href":"flutter_beacon_plugin/RangingResult/region.html","type":"property","overriddenDepth":0,"enclosedBy":{"name":"RangingResult","type":"class"}},{"name":"runtimeType","qualifiedName":"flutter_beacon_plugin.RangingResult.runtimeType","href":"flutter_beacon_plugin/RangingResult/runtimeType.html","type":"property","overriddenDepth":0,"enclosedBy":{"name":"RangingResult","type":"class"}},{"name":"toMap","qualifiedName":"flutter_beacon_plugin.RangingResult.toMap","href":"flutter_beacon_plugin/RangingResult/toMap.html","type":"method","overriddenDepth":0,"enclosedBy":{"name":"RangingResult","type":"class"}},{"name":"toString","qualifiedName":"flutter_beacon_plugin.RangingResult.toString","href":"flutter_beacon_plugin/RangingResult/toString.html","type":"method","overriddenDepth":0,"enclosedBy":{"name":"RangingResult","type":"class"}},{"name":"Region","qualifiedName":"flutter_beacon_plugin.Region","href":"flutter_beacon_plugin/Region-class.html","type":"class","overriddenDepth":0,"enclosedBy":{"name":"flutter_beacon_plugin","type":"library"}},{"name":"operator ==","qualifiedName":"flutter_beacon_plugin.Region.==","href":"flutter_beacon_plugin/Region/operator_equals.html","type":"method","overriddenDepth":1,"enclosedBy":{"name":"Region","type":"class"}},{"name":"Region","qualifiedName":"flutter_beacon_plugin.Region.Region","href":"flutter_beacon_plugin/Region/Region.html","type":"constructor","overriddenDepth":0,"enclosedBy":{"name":"Region","type":"class"}},{"name":"Region.fromMap","qualifiedName":"flutter_beacon_plugin.Region.fromMap","href":"flutter_beacon_plugin/Region/Region.fromMap.html","type":"constructor","overriddenDepth":0,"enclosedBy":{"name":"Region","type":"class"}},{"name":"hashCode","qualifiedName":"flutter_beacon_plugin.Region.hashCode","href":"flutter_beacon_plugin/Region/hashCode.html","type":"property","overriddenDepth":0,"enclosedBy":{"name":"Region","type":"class"}},{"name":"identifier","qualifiedName":"flutter_beacon_plugin.Region.identifier","href":"flutter_beacon_plugin/Region/identifier.html","type":"property","overriddenDepth":0,"enclosedBy":{"name":"Region","type":"class"}},{"name":"major","qualifiedName":"flutter_beacon_plugin.Region.major","href":"flutter_beacon_plugin/Region/major.html","type":"property","overriddenDepth":0,"enclosedBy":{"name":"Region","type":"class"}},{"name":"minor","qualifiedName":"flutter_beacon_plugin.Region.minor","href":"flutter_beacon_plugin/Region/minor.html","type":"property","overriddenDepth":0,"enclosedBy":{"name":"Region","type":"class"}},{"name":"noSuchMethod","qualifiedName":"flutter_beacon_plugin.Region.noSuchMethod","href":"flutter_beacon_plugin/Region/noSuchMethod.html","type":"method","overriddenDepth":0,"enclosedBy":{"name":"Region","type":"class"}},{"name":"proximityUUID","qualifiedName":"flutter_beacon_plugin.Region.proximityUUID","href":"flutter_beacon_plugin/Region/proximityUUID.html","type":"property","overriddenDepth":0,"enclosedBy":{"name":"Region","type":"class"}},{"name":"runtimeType","qualifiedName":"flutter_beacon_plugin.Region.runtimeType","href":"flutter_beacon_plugin/Region/runtimeType.html","type":"property","overriddenDepth":0,"enclosedBy":{"name":"Region","type":"class"}},{"name":"toMap","qualifiedName":"flutter_beacon_plugin.Region.toMap","href":"flutter_beacon_plugin/Region/toMap.html","type":"method","overriddenDepth":0,"enclosedBy":{"name":"Region","type":"class"}},{"name":"toString","qualifiedName":"flutter_beacon_plugin.Region.toString","href":"flutter_beacon_plugin/Region/toString.html","type":"method","overriddenDepth":1,"enclosedBy":{"name":"Region","type":"class"}}]
